qtfind/Icon.png
qtfind/QAbout.py
qtfind/QCommon.py
qtfind/QFileSystem.py
qtfind/QFind.py
qtfind/QGenreal.py
qtfind/QHeader.py
qtfind/QLabelClick.py
qtfind/QPermissions.py
qtfind/QSpacers.py
qtfind/QTime.py
qtfind/__init__.py
qtfind/main.py
qtfind/settings.py
qtfind-1.0.3.dist-info/LICENSE
qtfind-1.0.3.dist-info/METADATA
qtfind-1.0.3.dist-info/WHEEL
qtfind-1.0.3.dist-info/entry_points.txt
qtfind-1.0.3.dist-info/top_level.txt
qtfind-1.0.3.dist-info/RECORD
