Metadata-Version: 2.1
Name: qtfind
Version: 1.0.3
Summary: graphical front-end for the linux find command
Home-page: https://github.com/amad3v/QtFind
Author: Mohamed Jouini
Author-email: amad3v@gmail.com
License: UNKNOWN
Project-URL: Bug Reports, https://github.com/amad3v/QtFind/issues
Project-URL: Releases, https://github.com/amad3v/QtFind/releases
Platform: UNKNOWN
Classifier: Development Status :: 5 - Production/Stable
Classifier: Environment :: X11 Applications :: Qt
Classifier: Intended Audience :: End Users/Desktop
Classifier: License :: OSI Approved :: GNU General Public License v3 or later (GPLv3+)
Classifier: Operating System :: POSIX :: Linux
Classifier: Programming Language :: Python :: 3.7
Classifier: Topic :: Utilities
Requires-Python: >=3.7
Requires-Dist: PyQt5
